[{"id": 144189214, "contestId": 1631, "creationTimeSeconds": 1643295389, "relativeTimeSeconds": 1289, "problem": {"contestId": 1631, "problemsetName": null, "index": "B", "name": "Fun with Even Subarrays", "type": "PROGRAMMING", "points": 1000.0, "rating": null, "tags": ["dp", "greedy"]}, "author": {"contestId": 1631, "members": [{"handle": "bayashi_cl", "name": null}], "participantType": "CONTESTANT", "teamId": null, "teamName": null, "ghost": false, "room": 503, "startTimeSeconds": 1643294100}, "programmingLanguage": "GNU C++17 (64)", "verdict": "OK", "testset": "TESTS", "passedTestCount": 30, "timeConsumedMillis": 31, "memoryConsumedBytes": 819200, "points": null}]