[{"id": 28608963, "epoch_second": 1642446225, "problem_id": "math_and_algorithm_ap", "contest_id": "math-and-algorithm", "user_id": "bayashi_cl", "language": "Nim (1.0.6)", "point": 1000.0, "length": 1569, "result": "AC", "execution_time": 7}, {"id": 28608994, "epoch_second": 1642446529, "problem_id": "math_and_algorithm_ap", "contest_id": "math-and-algorithm", "user_id": "bayashi_cl", "language": "Nim (1.0.6)", "point": 1000.0, "length": 1612, "result": "AC", "execution_time": 5}, {"id": 28609079, "epoch_second": 1642447554, "problem_id": "math_and_algorithm_ap", "contest_id": "math-and-algorithm", "user_id": "bayashi_cl", "language": "Nim (1.0.6)", "point": 1000.0, "length": 1721, "result": "AC", "execution_time": 9}]